acc2psql/__init__.py
acc2psql/__main__.py
acc2psql/to_psql.py
acc2psql-0.0.8.dist-info/LICENSE
acc2psql-0.0.8.dist-info/METADATA
acc2psql-0.0.8.dist-info/WHEEL
acc2psql-0.0.8.dist-info/top_level.txt
acc2psql-0.0.8.dist-info/RECORD
