Metadata-Version: 2.1
Name: acc2psql
Version: 0.0.8
Summary: Converter from *.accdb/*.mdb to PostgreSQL *.sql
Home-page: https://github.com/remoteworkerid/acc2psql
Author: Eko S. Wibowo
Author-email: swdev.bali@gmail.com
License: UNKNOWN
Platform: UNKNOWN
Classifier: Programming Language :: Python :: 3
Classifier: License :: OSI Approved :: GNU General Public License v3 (GPLv3)
Classifier: Operating System :: OS Independent
Classifier: Development Status :: 4 - Beta
Requires-Python: >=3.6
Requires-Dist: pyodbc
Requires-Dist: click
Requires-Dist: psycopg2-binary
